.gitignore
README.md
setup.py
docs/Makefile
docs/conf.py
docs/index.rst
docs/make.bat
docs/_themes/LICENSE
docs/_themes/README.rst
docs/_themes/flask_theme_support.py
docs/_themes/kr/layout.html
docs/_themes/kr/relations.html
docs/_themes/kr/theme.conf
docs/_themes/kr/static/flasky.css_t
docs/_themes/kr/static/small_flask.css
docs/_themes/kr_small/layout.html
docs/_themes/kr_small/theme.conf
docs/_themes/kr_small/static/flasky.css_t
indicngram/__init__.py
indicngram/core.py
indicngram.egg-info/PKG-INFO
indicngram.egg-info/SOURCES.txt
indicngram.egg-info/dependency_links.txt
indicngram.egg-info/not-zip-safe
indicngram.egg-info/requires.txt
indicngram.egg-info/top_level.txt
indicngram/templates/indicngram.html
tests/__init__.py
tests/indicngrams_test.py