Metadata-Version: 1.0
Name: indicngram
Version: 0.4
Summary: n-gram genereator for indic languages
Home-page: http://silpa.org.in/NGram
Author: Santhosh Thottingal
Author-email: santhosh.thottingal@gmail.com
License: LGPL-3.0
Platform: UNKNOWN
